{
  "swagger": "2.0",
  "info": {
    "title": "apis/v1/server_instance_api.proto",
    "version": "version not set"
  },
  "tags": [
    {
      "name": "ServerInstanceService"
    }
  ],
  "consumes": [
    "application/json"
  ],
  "produces": [
    "application/json"
  ],
  "paths": {},
  "definitions": {
    "protobufAny": {
      "type": "object",
      "properties": {
        "@type": {
          "type": "string"
        }
      },
      "additionalProperties": {}
    },
    "rpcStatus": {
      "type": "object",
      "properties": {
        "code": {
          "type": "integer",
          "format": "int32"
        },
        "message": {
          "type": "string"
        },
        "details": {
          "type": "array",
          "items": {
            "type": "object",
            "$ref": "#/definitions/protobufAny"
          }
        }
      }
    },
    "v1GetStreamerIdResponse": {
      "type": "object",
      "properties": {
        "id": {
          "type": "string"
        }
      }
    },
    "v1InstanceConfig": {
      "type": "object",
      "properties": {
        "name": {
          "type": "string"
        },
        "cloudRes": {
          "type": "string"
        },
        "execPath": {
          "type": "string"
        },
        "launchArguments": {
          "type": "array",
          "items": {
            "type": "string"
          }
        },
        "metadata": {
          "type": "string"
        },
        "paksConfig": {
          "type": "string"
        },
        "faultRecover": {
          "type": "boolean"
        },
        "enableRelay": {
          "type": "boolean"
        },
        "enableRenderControl": {
          "type": "boolean"
        },
        "enableMultiuserControl": {
          "type": "boolean"
        },
        "autoControl": {
          "type": "boolean"
        },
        "stopDelay": {
          "type": "integer",
          "format": "int32"
        }
      }
    },
    "v1InstanceInfo": {
      "type": "object",
      "properties": {
        "id": {
          "type": "integer",
          "format": "int64"
        },
        "pid": {
          "type": "integer",
          "format": "int32"
        },
        "stateCode": {
          "type": "integer",
          "format": "int32"
        },
        "streamerConnected": {
          "type": "boolean"
        },
        "streamerId": {
          "type": "string"
        },
        "lastStartAt": {
          "type": "string",
          "format": "date-time"
        },
        "lastStopAt": {
          "type": "string",
          "format": "date-time"
        },
        "config": {
          "$ref": "#/definitions/v1InstanceConfig"
        },
        "playerConfig": {
          "$ref": "#/definitions/v1PlayerConfig"
        }
      }
    },
    "v1PlayerConfig": {
      "type": "object",
      "properties": {
        "matchViewportRes": {
          "type": "boolean"
        },
        "hideUi": {
          "type": "boolean"
        },
        "idleDisconnect": {
          "type": "boolean"
        },
        "idleTimeout": {
          "type": "integer",
          "format": "int64"
        }
      }
    }
  }
}
